smear/__init__.py
smear/file_identifier.py
smear/runner.py
smear/smearing.py
smear/uiterm.py
smear/version.py
smear-0.1.6.dist-info/LICENSE
smear-0.1.6.dist-info/METADATA
smear-0.1.6.dist-info/WHEEL
smear-0.1.6.dist-info/entry_points.txt
smear-0.1.6.dist-info/top_level.txt
smear-0.1.6.dist-info/RECORD
