Metadata-Version: 2.1
Name: smear
Version: 0.1.6
Summary: Clear CLI interface for smearing
Home-page: https://gitlab.com/eic/escalate/smear
Author: Dmitry Romanov
Author-email: romanov@jlab.org
License: MIT
Platform: UNKNOWN
Classifier: Development Status :: 4 - Beta
Classifier: License :: OSI Approved :: MIT License
Classifier: Programming Language :: Python :: 2
Classifier: Programming Language :: Python :: 2.7
Classifier: Programming Language :: Python :: 3
Classifier: Programming Language :: Python :: 3.6
Requires-Dist: pyjano
